<?xml version="1.0" encoding="UTF-8"?>
<MetaDataObject xmlns="http://v8.1c.ru/8.3/MDClasses" xmlns:app="http://v8.1c.ru/8.2/managed-application/core" xmlns:cfg="http://v8.1c.ru/8.1/data/enterprise/current-config" xmlns:cmi="http://v8.1c.ru/8.2/managed-application/cmi" xmlns:ent="http://v8.1c.ru/8.1/data/enterprise" xmlns:lf="http://v8.1c.ru/8.2/managed-application/logform" xmlns:style="http://v8.1c.ru/8.1/data/ui/style" xmlns:sys="http://v8.1c.ru/8.1/data/ui/fonts/system" xmlns:v8="http://v8.1c.ru/8.1/data/core" xmlns:v8ui="http://v8.1c.ru/8.1/data/ui" xmlns:web="http://v8.1c.ru/8.1/data/ui/colors/web" xmlns:win="http://v8.1c.ru/8.1/data/ui/colors/windows" xmlns:xen="http://v8.1c.ru/8.3/xcf/enums" xmlns:xpr="http://v8.1c.ru/8.3/xcf/predef" xmlns:xr="http://v8.1c.ru/8.3/xcf/readable" xmlns:xs="http://www.w3.org/2001/XMLSchema" xmlns:xsi="http://www.w3.org/2001/XMLSchema-instance">
	<InformationRegister uuid="3ff5f9e0-bd99-475d-8594-8e3874fac5f9">
		<InnerInfo>
			<xr:producedType name="InformationRegisterRecord.АктуальныеЗадачиДляОповещения" category="Record">
				<xr:typeId>307cf423-96f6-4070-9879-e0d8d182e28c</xr:typeId>
				<xr:valTypeId>ede0dc34-e099-423b-b9fd-bc7fc01b4025</xr:valTypeId>
			</xr:producedType>
			<xr:producedType name="InformationRegisterManager.АктуальныеЗадачиДляОповещения" category="Manager">
				<xr:typeId>55499c94-32db-4972-85c6-8fb9aeefa4d4</xr:typeId>
				<xr:valTypeId>698eed0e-6063-41d1-9129-e6120e88e945</xr:valTypeId>
			</xr:producedType>
			<xr:producedType name="InformationRegisterSelection.АктуальныеЗадачиДляОповещения" category="Selection">
				<xr:typeId>c0e94935-3f42-4d19-93c1-a26de8eaff26</xr:typeId>
				<xr:valTypeId>29ded31d-700f-435c-bef6-070439b627eb</xr:valTypeId>
			</xr:producedType>
			<xr:producedType name="InformationRegisterList.АктуальныеЗадачиДляОповещения" category="List">
				<xr:typeId>096bd528-6d19-442e-a18f-3bc31b7d7a79</xr:typeId>
				<xr:valTypeId>ad608ca3-c8d2-4997-80d1-22a598a37f8b</xr:valTypeId>
			</xr:producedType>
			<xr:producedType name="InformationRegisterRecordSet.АктуальныеЗадачиДляОповещения" category="RecordSet">
				<xr:typeId>249fc572-2d1c-4fbb-b8fc-6cce53896b05</xr:typeId>
				<xr:valTypeId>2bc5c69e-808a-4801-8f7a-52e2657483d8</xr:valTypeId>
			</xr:producedType>
			<xr:producedType name="InformationRegisterRecordKey.АктуальныеЗадачиДляОповещения" category="RecordKey">
				<xr:typeId>4ca74eb3-6a20-44bd-a700-875f14881502</xr:typeId>
				<xr:valTypeId>7065ebb4-973c-4e96-b90c-0f1c4966c0a4</xr:valTypeId>
			</xr:producedType>
			<xr:producedType name="InformationRegisterRecordManager.АктуальныеЗадачиДляОповещения" category="RecordManager">
				<xr:typeId>79477a68-38ed-4c23-8c40-ecc0881cd342</xr:typeId>
				<xr:valTypeId>f58ef8bd-90dc-4758-bcb3-e4e563ec16a6</xr:valTypeId>
			</xr:producedType>
		</InnerInfo>
		<Properties>
			<Name>АктуальныеЗадачиДляОповещения</Name>
			<Synonym>
				<v8:item>
					<v8:lang>ru</v8:lang>
					<v8:content>Актуальные задачи для оповещения</v8:content>
				</v8:item>
			</Synonym>
			<Comment/>
			<UseStandardCommands>true</UseStandardCommands>
			<EditType>InDialog</EditType>
			<DefaultRecordForm/>
			<DefaultListForm/>
			<AuxiliaryRecordForm/>
			<AuxiliaryListForm/>
			<StandardAttributes>
				<xr:Attribute name="Active">
					<xr:LinkByType/>
					<xr:FillChecking>DontCheck</xr:FillChecking>
					<xr:MultiLine>false</xr:MultiLine>
					<xr:FillFromFillingValue>false</xr:FillFromFillingValue>
					<xr:CreateOnInput>Auto</xr:CreateOnInput>
					<xr:MaxValue xsi:nil="true"/>
					<xr:ToolTip/>
					<xr:ExtendedEdit>false</xr:ExtendedEdit>
					<xr:Format/>
					<xr:ChoiceForm/>
					<xr:QuickChoice>Auto</xr:QuickChoice>
					<xr:EditFormat/>
					<xr:PasswordMode>false</xr:PasswordMode>
					<xr:MarkNegatives>false</xr:MarkNegatives>
					<xr:MinValue xsi:nil="true"/>
					<xr:Synonym/>
					<xr:Comment/>
					<xr:FullTextSearch>Use</xr:FullTextSearch>
					<xr:ChoiceParameterLinks/>
					<xr:FillValue xsi:nil="true"/>
					<xr:Mask/>
					<xr:ChoiceParameters/>
				</xr:Attribute>
				<xr:Attribute name="LineNumber">
					<xr:LinkByType/>
					<xr:FillChecking>DontCheck</xr:FillChecking>
					<xr:MultiLine>false</xr:MultiLine>
					<xr:FillFromFillingValue>false</xr:FillFromFillingValue>
					<xr:CreateOnInput>Auto</xr:CreateOnInput>
					<xr:MaxValue xsi:nil="true"/>
					<xr:ToolTip/>
					<xr:ExtendedEdit>false</xr:ExtendedEdit>
					<xr:Format/>
					<xr:ChoiceForm/>
					<xr:QuickChoice>Auto</xr:QuickChoice>
					<xr:EditFormat/>
					<xr:PasswordMode>false</xr:PasswordMode>
					<xr:MarkNegatives>false</xr:MarkNegatives>
					<xr:MinValue xsi:nil="true"/>
					<xr:Synonym/>
					<xr:Comment/>
					<xr:FullTextSearch>Use</xr:FullTextSearch>
					<xr:ChoiceParameterLinks/>
					<xr:FillValue xsi:nil="true"/>
					<xr:Mask/>
					<xr:ChoiceParameters/>
				</xr:Attribute>
				<xr:Attribute name="Recorder">
					<xr:LinkByType/>
					<xr:FillChecking>DontCheck</xr:FillChecking>
					<xr:MultiLine>false</xr:MultiLine>
					<xr:FillFromFillingValue>false</xr:FillFromFillingValue>
					<xr:CreateOnInput>Auto</xr:CreateOnInput>
					<xr:MaxValue xsi:nil="true"/>
					<xr:ToolTip/>
					<xr:ExtendedEdit>false</xr:ExtendedEdit>
					<xr:Format/>
					<xr:ChoiceForm/>
					<xr:QuickChoice>Auto</xr:QuickChoice>
					<xr:EditFormat/>
					<xr:PasswordMode>false</xr:PasswordMode>
					<xr:MarkNegatives>false</xr:MarkNegatives>
					<xr:MinValue xsi:nil="true"/>
					<xr:Synonym/>
					<xr:Comment/>
					<xr:FullTextSearch>Use</xr:FullTextSearch>
					<xr:ChoiceParameterLinks/>
					<xr:FillValue xsi:nil="true"/>
					<xr:Mask/>
					<xr:ChoiceParameters/>
				</xr:Attribute>
				<xr:Attribute name="Period">
					<xr:LinkByType/>
					<xr:FillChecking>ShowError</xr:FillChecking>
					<xr:MultiLine>false</xr:MultiLine>
					<xr:FillFromFillingValue>false</xr:FillFromFillingValue>
					<xr:CreateOnInput>Auto</xr:CreateOnInput>
					<xr:MaxValue xsi:nil="true"/>
					<xr:ToolTip/>
					<xr:ExtendedEdit>false</xr:ExtendedEdit>
					<xr:Format/>
					<xr:ChoiceForm/>
					<xr:QuickChoice>Auto</xr:QuickChoice>
					<xr:EditFormat/>
					<xr:PasswordMode>false</xr:PasswordMode>
					<xr:MarkNegatives>false</xr:MarkNegatives>
					<xr:MinValue xsi:nil="true"/>
					<xr:Synonym/>
					<xr:Comment/>
					<xr:FullTextSearch>Use</xr:FullTextSearch>
					<xr:ChoiceParameterLinks/>
					<xr:FillValue xsi:nil="true"/>
					<xr:Mask/>
					<xr:ChoiceParameters/>
				</xr:Attribute>
			</StandardAttributes>
			<InformationRegisterPeriodicity>Nonperiodical</InformationRegisterPeriodicity>
			<WriteMode>Independent</WriteMode>
			<MainFilterOnPeriod>false</MainFilterOnPeriod>
			<IncludeHelpInContents>true</IncludeHelpInContents>
			<DataLockControlMode>Managed</DataLockControlMode>
			<FullTextSearch>DontUse</FullTextSearch>
			<EnableTotalsSliceFirst>false</EnableTotalsSliceFirst>
			<EnableTotalsSliceLast>false</EnableTotalsSliceLast>
			<RecordPresentation>
				<v8:item>
					<v8:lang>ru</v8:lang>
					<v8:content>Актуальная задача</v8:content>
				</v8:item>
			</RecordPresentation>
			<ExtendedRecordPresentation/>
			<ListPresentation/>
			<ExtendedListPresentation/>
			<Explanation/>
		</Properties>
		<ChildObjects>
			<Resource uuid="4e54106a-84a8-4758-ae7b-84c7729155f8">
				<Properties>
					<Name>Значение</Name>
					<Synonym>
						<v8:item>
							<v8:lang>ru</v8:lang>
							<v8:content>Значение</v8:content>
						</v8:item>
					</Synonym>
					<Comment/>
					<Type>
						<v8:TypeSet>cfg:DocumentRef</v8:TypeSet>
						<v8:TypeSet>cfg:CatalogRef</v8:TypeSet>
					</Type>
					<PasswordMode>false</PasswordMode>
					<Format/>
					<EditFormat/>
					<ToolTip/>
					<MarkNegatives>false</MarkNegatives>
					<Mask/>
					<MultiLine>false</MultiLine>
					<ExtendedEdit>false</ExtendedEdit>
					<MinValue xsi:nil="true"/>
					<MaxValue xsi:nil="true"/>
					<FillFromFillingValue>true</FillFromFillingValue>
					<FillValue xsi:nil="true"/>
					<FillChecking>DontCheck</FillChecking>
					<ChoiceFoldersAndItems>Items</ChoiceFoldersAndItems>
					<ChoiceParameterLinks/>
					<ChoiceParameters/>
					<QuickChoice>Auto</QuickChoice>
					<CreateOnInput>Auto</CreateOnInput>
					<ChoiceForm/>
					<LinkByType/>
					<Indexing>DontIndex</Indexing>
					<FullTextSearch>Use</FullTextSearch>
				</Properties>
			</Resource>
			<Dimension uuid="1ecb35f3-7e3e-4ecc-a0cf-ec37ab522e60">
				<Properties>
					<Name>Пользователь</Name>
					<Synonym>
						<v8:item>
							<v8:lang>ru</v8:lang>
							<v8:content>Пользователь</v8:content>
						</v8:item>
					</Synonym>
					<Comment/>
					<Type>
						<v8:Type>cfg:CatalogRef.Пользователи</v8:Type>
					</Type>
					<PasswordMode>false</PasswordMode>
					<Format/>
					<EditFormat/>
					<ToolTip/>
					<MarkNegatives>false</MarkNegatives>
					<Mask/>
					<MultiLine>false</MultiLine>
					<ExtendedEdit>false</ExtendedEdit>
					<MinValue xsi:nil="true"/>
					<MaxValue xsi:nil="true"/>
					<FillFromFillingValue>true</FillFromFillingValue>
					<FillValue xsi:nil="true"/>
					<FillChecking>DontCheck</FillChecking>
					<ChoiceFoldersAndItems>Items</ChoiceFoldersAndItems>
					<ChoiceParameterLinks/>
					<ChoiceParameters/>
					<QuickChoice>Auto</QuickChoice>
					<CreateOnInput>Auto</CreateOnInput>
					<ChoiceForm/>
					<LinkByType/>
					<Master>true</Master>
					<MainFilter>true</MainFilter>
					<DenyIncompleteValues>true</DenyIncompleteValues>
					<Indexing>DontIndex</Indexing>
					<FullTextSearch>Use</FullTextSearch>
				</Properties>
			</Dimension>
			<Dimension uuid="15a08ff5-002a-41eb-9f4d-2547336b2753">
				<Properties>
					<Name>ОписательОповещения</Name>
					<Synonym>
						<v8:item>
							<v8:lang>ru</v8:lang>
							<v8:content>Описатель оповещения</v8:content>
						</v8:item>
					</Synonym>
					<Comment/>
					<Type>
						<v8:Type>xs:string</v8:Type>
						<v8:StringQualifiers>
							<v8:Length>100</v8:Length>
							<v8:AllowedLength>Variable</v8:AllowedLength>
						</v8:StringQualifiers>
					</Type>
					<PasswordMode>false</PasswordMode>
					<Format/>
					<EditFormat/>
					<ToolTip/>
					<MarkNegatives>false</MarkNegatives>
					<Mask/>
					<MultiLine>false</MultiLine>
					<ExtendedEdit>false</ExtendedEdit>
					<MinValue xsi:nil="true"/>
					<MaxValue xsi:nil="true"/>
					<FillFromFillingValue>false</FillFromFillingValue>
					<FillValue xsi:type="xs:string"/>
					<FillChecking>DontCheck</FillChecking>
					<ChoiceFoldersAndItems>Items</ChoiceFoldersAndItems>
					<ChoiceParameterLinks/>
					<ChoiceParameters/>
					<QuickChoice>Auto</QuickChoice>
					<CreateOnInput>Auto</CreateOnInput>
					<ChoiceForm/>
					<LinkByType/>
					<Master>false</Master>
					<MainFilter>true</MainFilter>
					<DenyIncompleteValues>true</DenyIncompleteValues>
					<Indexing>DontIndex</Indexing>
					<FullTextSearch>Use</FullTextSearch>
				</Properties>
			</Dimension>
		</ChildObjects>
	</InformationRegister>
</MetaDataObject>